mppm/run.py
mppm/src/__init__.py
mppm/src/command/argpass.py
mppm/src/command/cmd_dispatch.py
mppm/src/command/download.py
mppm/src/command/rewrite.py
mppm/src/command/uninstall.py
mppm/src/common/const.py
mppm/src/common/utility.py
mppm/src/config/pip_conf.py
mppm-3.0.9.dist-info/LICENSE
mppm-3.0.9.dist-info/METADATA
mppm-3.0.9.dist-info/WHEEL
mppm-3.0.9.dist-info/entry_points.txt
mppm-3.0.9.dist-info/top_level.txt
mppm-3.0.9.dist-info/RECORD
