Metadata-Version: 2.1
Name: mppm
Version: 3.0.9
Summary: Manager Pypi Package & Mirror
Home-page: https://gitee.com/TianCiwang/mppm.git
Author: TianCiwang
Author-email: 13623650548@163.com
License: MIT
Keywords: pypi,mirror,package
Platform: UNKNOWN
Classifier: Development Status :: 4 - Beta
Classifier: Intended Audience :: Developers
Classifier: License :: OSI Approved :: MIT License
Classifier: Programming Language :: Python :: 3.6
Classifier: Programming Language :: Python :: 3.7
Classifier: Programming Language :: Python :: 3.8
Classifier: Programming Language :: Python :: 3.9
Classifier: Programming Language :: Python :: 3.10
License-File: LICENSE
Requires-Dist: pip
Requires-Dist: crayons
Requires-Dist: blindspin
Requires-Dist: requests
Requires-Dist: pick (==1.3.1)
Requires-Dist: configparser
Requires-Dist: pip-autoremove
Requires-Dist: pip2pi
